LICENSE
README.md
setup.py
inputvalidation/__init__.py
inputvalidation/validator.py
inputvalidation/validators.py
inputvalidation.egg-info/PKG-INFO
inputvalidation.egg-info/SOURCES.txt
inputvalidation.egg-info/dependency_links.txt
inputvalidation.egg-info/top_level.txt