Metadata-Version: 2.1
Name: inputvalidation
Version: 1.1.3
Summary: A python module to validate input.
Home-page: https://github.com/Matthias1590/InputValidation
Author: Matthias Wijnsma
Author-email: matthiasx95@gmail.com
License: MIT
Platform: UNKNOWN
License-File: LICENSE
